Rocket_simple_Trajectory_Project/__init__.py
Rocket_simple_Trajectory_Project/main.py
rocket_simple_trajectory_project-0.1.0.dist-info/METADATA
rocket_simple_trajectory_project-0.1.0.dist-info/WHEEL
rocket_simple_trajectory_project-0.1.0.dist-info/RECORD
